datafast/__init__.py
datafast/card_utils.py
datafast/datasets.py
datafast/expanders.py
datafast/inspectors.py
datafast/llm_utils.py
datafast/llms.py
datafast/logger_config.py
datafast/utils.py
datafast/examples/classification_trail_conditions_example.py
datafast/examples/generic_pipeline_example.py
datafast/examples/generic_pipeline_response_format_example.py
datafast/examples/generic_pipeline_row_model_example.py
datafast/examples/inspect_dataset_example.py
datafast/examples/keywords_extraction_example.py
datafast/examples/mcq_contextual_example.py
datafast/examples/mcq_example.py
datafast/examples/preference_dataset_example.py
datafast/examples/quickstart_example.py
datafast/examples/raw_text_space_engineering_example.py
datafast/examples/show_dataset_examples.py
datafast/examples/ultrachat_materials_science.py
datafast/prompts/__init__.py
datafast/prompts/classification_prompts.py
datafast/prompts/mcq_prompts.py
datafast/prompts/preference_prompts.py
datafast/prompts/question_generation_prompts.py
datafast/prompts/text_prompts.py
datafast/schema/config.py
datafast/schema/data_rows.py
datafast-0.0.31.dist-info/licenses/LICENSE
datafast-0.0.31.dist-info/METADATA
datafast-0.0.31.dist-info/WHEEL
datafast-0.0.31.dist-info/top_level.txt
datafast-0.0.31.dist-info/RECORD
