Metadata-Version: 2.4
Name: datafast
Version: 0.0.31
Summary: A Python package for synthetic text dataset generation
Author: Patrick Fleith
License: 
Project-URL: Documentation, https://github.com/patrickfleith/datafast
Project-URL: Issue Tracker, https://github.com/patrickfleith/datafast/issues
Project-URL: Discussions, https://github.com/patrickfleith/datafast/discussions
Keywords: dataset,text,generation
Classifier: Development Status :: 3 - Alpha
Classifier: Intended Audience :: Developers
Classifier: License :: OSI Approved :: Apache Software License
Classifier: Programming Language :: Python :: 3.10
Classifier: Programming Language :: Python :: 3.11
Classifier: Programming Language :: Python :: 3.12
Classifier: Programming Language :: Python :: 3.13
Requires-Python: >=3.10
License-File: LICENSE
Requires-Dist: datasets>=3.0
Requires-Dist: instructor
Requires-Dist: google-generativeai
Requires-Dist: python-dotenv
Requires-Dist: anthropic
Requires-Dist: openai
Requires-Dist: pydantic
Requires-Dist: litellm
Requires-Dist: gradio
Requires-Dist: loguru
Provides-Extra: dev
Requires-Dist: pytest>=6.0; extra == "dev"
Requires-Dist: ruff>=0.9.0; extra == "dev"
Dynamic: license-file
